gecko_libs/__init__.py
gecko_libs/codehandler.py
gecko_libs/gct.py
gecko_libs/geckocode.py
gecko_libs/workpathing.py
geckolibs/__init__.py
geckolibs/codehandler.py
geckolibs/gct.py
geckolibs/geckocode.py
geckolibs/workpathing.py
geckolibs-0.2.3.dist-info/LICENSE
geckolibs-0.2.3.dist-info/METADATA
geckolibs-0.2.3.dist-info/WHEEL
geckolibs-0.2.3.dist-info/top_level.txt
geckolibs-0.2.3.dist-info/RECORD
